[
  {
    "text": "дата-саентист ml nlp python pandas cv желателен опыт английский омск можно с релокацией",
    "intent": "inform",
    "intent_prediction": {
      "name": "telling_language_needed",
      "confidence": 0.45059946179389954
    }
  },
  {
    "text": "омск",
    "intent": "telling_location",
    "intent_prediction": {
      "name": "inform",
      "confidence": 0.9998753070831299
    }
  },
  {
    "text": "Омск",
    "intent": "telling_location",
    "intent_prediction": {
      "name": "inform",
      "confidence": 0.9999446868896484
    }
  },
  {
    "text": "а что если поискать с опытом не только в java но и C",
    "intent": "telling_hardskills",
    "intent_prediction": {
      "name": "init_new_search",
      "confidence": 0.24403636157512665
    }
  },
  {
    "text": "python, django, djangoREST, mongo DB",
    "intent": "telling_hardskills",
    "intent_prediction": {
      "name": "inform",
      "confidence": 0.9561442136764526
    }
  },
  {
    "text": "программист java москва 5 лет опыта",
    "intent": "telling_experience",
    "intent_prediction": {
      "name": "inform",
      "confidence": 0.7130748629570007
    }
  },
  {
    "text": "english, advanced",
    "intent": "telling_language_needed",
    "intent_prediction": {
      "name": "telling_hardskills",
      "confidence": 0.45297497510910034
    }
  },
  {
    "text": "найти",
    "intent": "init_searching",
    "intent_prediction": {
      "name": "greeting",
      "confidence": 0.32855698466300964
    }
  }
]